azure/communication/callautomation/__init__.py
azure/communication/callautomation/_api_versions.py
azure/communication/callautomation/_call_automation_client.py
azure/communication/callautomation/_call_connection_client.py
azure/communication/callautomation/_content_downloader.py
azure/communication/callautomation/_models.py
azure/communication/callautomation/_utils.py
azure/communication/callautomation/_version.py
azure/communication/callautomation/py.typed
azure/communication/callautomation/_credential/__init__.py
azure/communication/callautomation/_credential/call_automation_auth_policy_utils.py
azure/communication/callautomation/_credential/call_automation_policy.py
azure/communication/callautomation/_credential/credential_utils.py
azure/communication/callautomation/_generated/__init__.py
azure/communication/callautomation/_generated/_client.py
azure/communication/callautomation/_generated/_configuration.py
azure/communication/callautomation/_generated/_patch.py
azure/communication/callautomation/_generated/py.typed
azure/communication/callautomation/_generated/_utils/__init__.py
azure/communication/callautomation/_generated/_utils/serialization.py
azure/communication/callautomation/_generated/_utils/utils.py
azure/communication/callautomation/_generated/aio/__init__.py
azure/communication/callautomation/_generated/aio/_client.py
azure/communication/callautomation/_generated/aio/_configuration.py
azure/communication/callautomation/_generated/aio/_patch.py
azure/communication/callautomation/_generated/aio/operations/__init__.py
azure/communication/callautomation/_generated/aio/operations/_operations.py
azure/communication/callautomation/_generated/aio/operations/_patch.py
azure/communication/callautomation/_generated/models/__init__.py
azure/communication/callautomation/_generated/models/_enums.py
azure/communication/callautomation/_generated/models/_models.py
azure/communication/callautomation/_generated/models/_patch.py
azure_communication_callautomation-1.4.0.dist-info/LICENSE
azure_communication_callautomation-1.4.0.dist-info/METADATA
azure_communication_callautomation-1.4.0.dist-info/WHEEL
azure_communication_callautomation-1.4.0.dist-info/top_level.txt
azure_communication_callautomation-1.4.0.dist-info/RECORD
